{
    "__comment": "Model generated using MrCrayfish's Model Creator (http://mrcrayfish.com/modelcreator/)",
    "textures": {
        "0": "aetherworks:blocks/heater"
    },
    "elements": [
        {
            "name": "Base",
            "from": [ 2.0, 0.0, 0.0 ], 
            "to": [ 14.0, 3.0, 12.0 ], 
            "faces": {
                "north": { "texture": "#0", "uv": [ 4.0, 1.0, 8.0, 2.0 ] },
                "east": { "texture": "#0", "uv": [ 4.0, 1.0, 8.0, 2.0 ] },
                "south": { "texture": "#0", "uv": [ 4.0, 1.0, 8.0, 2.0 ] },
                "west": { "texture": "#0", "uv": [ 4.0, 1.0, 8.0, 2.0 ] },
                "up": { "texture": "#0", "uv": [ 4.0, 0.0, 8.0, 4.0 ] },
                "down": { "texture": "#0", "uv": [ 4.0, 0.0, 8.0, 4.0 ] }
            }
        },
        {
            "name": "Connection",
            "from": [ 3.0, 3.0, 15.0 ], 
            "to": [ 13.0, 13.0, 16.0 ], 
            "faces": {
                "north": { "texture": "#0", "uv": [ 8.0, 0.0, 12.0, 4.0 ] },
                "east": { "texture": "#0", "uv": [ 8.0, 0.0, 9.0, 4.0 ] },
                "south": { "texture": "#0", "uv": [ 8.0, 0.0, 12.0, 4.0 ] },
                "west": { "texture": "#0", "uv": [ 8.0, 0.0, 9.0, 4.0 ] },
                "up": { "texture": "#0", "uv": [ 8.0, 0.0, 12.0, 1.0 ] },
                "down": { "texture": "#0", "uv": [ 8.0, 0.0, 12.0, 1.0 ] }
            }
        },
        {
            "name": "Connection",
            "from": [ 5.0, 5.0, 14.0 ], 
            "to": [ 11.0, 11.0, 15.0 ], 
            "faces": {
                "north": { "texture": "#0", "uv": [ 8.0, 0.0, 12.0, 4.0 ] },
                "east": { "texture": "#0", "uv": [ 8.0, 0.0, 9.0, 4.0 ] },
                "south": { "texture": "#0", "uv": [ 8.0, 0.0, 12.0, 4.0 ] },
                "west": { "texture": "#0", "uv": [ 8.0, 0.0, 9.0, 4.0 ] },
                "up": { "texture": "#0", "uv": [ 8.0, 0.0, 12.0, 1.0 ] },
                "down": { "texture": "#0", "uv": [ 8.0, 0.0, 12.0, 1.0 ] }
            }
        },
        {
            "name": "Connection",
            "from": [ 6.0, 6.0, 9.0 ], 
            "to": [ 10.0, 10.0, 14.0 ], 
            "faces": {
                "north": { "texture": "#0", "uv": [ 8.0, 0.0, 12.0, 4.0 ] },
                "east": { "texture": "#0", "uv": [ 8.0, 0.0, 12.0, 4.0 ] },
                "south": { "texture": "#0", "uv": [ 8.0, 0.0, 12.0, 4.0 ] },
                "west": { "texture": "#0", "uv": [ 8.0, 0.0, 12.0, 4.0 ] },
                "up": { "texture": "#0", "uv": [ 8.0, 0.0, 12.0, 4.0 ] },
                "down": { "texture": "#0", "uv": [ 8.0, 0.0, 12.0, 4.0 ] }
            }
        },
        {
            "name": "Container",
            "from": [ 5.0, 5.0, 3.0 ], 
            "to": [ 11.0, 11.0, 9.0 ], 
            "faces": {
                "north": { "texture": "#0", "uv": [ 4.0, 4.0, 8.0, 8.0 ] },
                "east": { "texture": "#0", "uv": [ 4.0, 4.0, 8.0, 8.0 ] },
                "south": { "texture": "#0", "uv": [ 4.0, 4.0, 8.0, 8.0 ] },
                "west": { "texture": "#0", "uv": [ 4.0, 4.0, 8.0, 8.0 ] },
                "up": { "texture": "#0", "uv": [ 4.0, 4.0, 8.0, 8.0 ] },
                "down": { "texture": "#0", "uv": [ 4.0, 4.0, 8.0, 8.0 ] }
            }
        },
        {
            "name": "EmberConnector",
            "from": [ 5.0, 12.0, 5.0 ], 
            "to": [ 11.0, 14.0, 11.0 ],
            "faces": {
                "north": { "texture": "#0", "uv": [ 0.0, 3.5, 4.0, 6.5 ] },
                "east": { "texture": "#0", "uv": [ 0.0, 3.5, 4.0, 6.5 ] },
                "south": { "texture": "#0", "uv": [ 0.0, 3.5, 4.0, 6.5 ] },
                "west": { "texture": "#0", "uv": [ 0.0, 3.5, 4.0, 6.5 ] },
                "up": { "texture": "#0", "uv": [ 0.0, 0.0, 4.0, 4.0 ] },
                "down": { "texture": "#0", "uv": [ 0.0, 0.0, 4.0, 4.0 ] }
            }
        },
        {
            "name": "FluidConnector",
            "from": [ 0.0, 6.0, 6.0 ], 
            "to": [ 1.0, 10.0, 10.0 ], 
            "faces": {
                "north": { "texture": "#0", "uv": [ 0.0, 6.5, 0.5, 8.5 ] },
                "east": { "texture": "#0", "uv": [ 0.0, 6.5, 2.0, 8.5 ] },
                "south": { "texture": "#0", "uv": [ 0.0, 6.5, 0.5, 8.5 ] },
                "west": { "texture": "#0", "uv": [ 0.0, 6.5, 2.0, 8.5 ] },
                "up": { "texture": "#0", "uv": [ 0.0, 6.5, 0.5, 8.5 ] },
                "down": { "texture": "#0", "uv": [ 0.0, 6.5, 0.5, 8.5 ] }
            }
        },
        {
            "name": "FluidConnector",
            "from": [ 15.0, 6.0, 6.0 ], 
            "to": [ 16.0, 10.0, 10.0 ], 
            "faces": {
                "north": { "texture": "#0", "uv": [ 0.0, 6.5, 0.5, 8.5 ] },
                "east": { "texture": "#0", "uv": [ 0.0, 6.5, 2.0, 8.5 ] },
                "south": { "texture": "#0", "uv": [ 0.0, 6.5, 0.5, 8.5 ] },
                "west": { "texture": "#0", "uv": [ 0.0, 6.5, 2.0, 8.5 ] },
                "up": { "texture": "#0", "uv": [ 0.0, 6.5, 0.5, 8.5 ] },
                "down": { "texture": "#0", "uv": [ 0.0, 6.5, 0.5, 8.5 ] }
            }
        },
        {
            "name": "FluidConnector",
            "from": [ 6.0, 6.0, 0.0 ], 
            "to": [ 10.0, 10.0, 1.0 ], 
            "faces": {
                "north": { "texture": "#0", "uv": [ 0.0, 6.5, 2.0, 8.5 ] },
                "east": { "texture": "#0", "uv": [ 0.0, 6.5, 0.5, 8.5 ] },
                "south": { "texture": "#0", "uv": [ 0.0, 6.5, 2.0, 8.0 ] },
                "west": { "texture": "#0", "uv": [ 0.0, 6.5, 0.5, 8.5 ] },
                "up": { "texture": "#0", "uv": [ 0.0, 6.5, 2.0, 7.0 ] },
                "down": { "texture": "#0", "uv": [ 0.0, 6.5, 2.0, 7.0 ] }
            }
        },
        {
            "name": "Pipe",
            "from": [ 0.5, 7.0, 7.0 ], 
            "to": [ 5.5, 9.0, 9.0 ], 
            "rotation": { "origin": [ 1.0, 8.0, 8.0 ], "axis": "y", "angle": 22.5 },
            "faces": {
                "north": { "texture": "#0", "uv": [ 4.0, 4.0, 8.0, 5.0 ] },
                "east": { "texture": "#0", "uv": [ 4.0, 4.0, 6.0, 6.0 ] },
                "south": { "texture": "#0", "uv": [ 4.0, 4.0, 8.0, 5.0 ] },
                "west": { "texture": "#0", "uv": [ 4.0, 4.0, 6.0, 6.0 ] },
                "up": { "texture": "#0", "uv": [ 4.0, 4.0, 8.0, 5.0 ] },
                "down": { "texture": "#0", "uv": [ 4.0, 4.0, 8.0, 5.0 ] }
            }
        },
        {
            "name": "Pipe",
            "from": [ 10.5, 7.0, 7.0 ], 
            "to": [ 15.5, 9.0, 9.0 ], 
            "rotation": { "origin": [ 15.0, 8.0, 8.0 ], "axis": "y", "angle": -22.5 },
            "faces": {
                "north": { "texture": "#0", "uv": [ 4.0, 4.0, 8.0, 5.0 ] },
                "east": { "texture": "#0", "uv": [ 4.0, 4.0, 6.0, 6.0 ] },
                "south": { "texture": "#0", "uv": [ 4.0, 4.0, 8.0, 5.0 ] },
                "west": { "texture": "#0", "uv": [ 4.0, 4.0, 6.0, 6.0 ] },
                "up": { "texture": "#0", "uv": [ 4.0, 4.0, 8.0, 5.0 ] },
                "down": { "texture": "#0", "uv": [ 4.0, 4.0, 8.0, 5.0 ] }
            }
        },
        {
            "name": "Pipe",
            "from": [ 7.0, 7.0, 1.0 ], 
            "to": [ 9.0, 9.0, 3.0 ], 
            "faces": {
                "north": { "texture": "#0", "uv": [ 4.0, 4.0, 6.0, 6.0 ] },
                "east": { "texture": "#0", "uv": [ 4.0, 4.0, 5.0, 5.0 ] },
                "south": { "texture": "#0", "uv": [ 4.0, 4.0, 6.0, 6.0 ] },
                "west": { "texture": "#0", "uv": [ 4.0, 4.0, 5.0, 5.0 ] },
                "up": { "texture": "#0", "uv": [ 4.0, 4.0, 5.0, 5.0 ] },
                "down": { "texture": "#0", "uv": [ 4.0, 4.0, 5.0, 5.0 ] }
            }
        },
        {
            "name": "Support",
            "from": [ 4.0, 3.0, 4.0 ], 
            "to": [ 6.0, 15.0, 6.0 ], 
            "faces": {
                "north": { "texture": "#0", "uv": [ 14.0, 0.0, 16.0, 8.0 ] },
                "east": { "texture": "#0", "uv": [ 14.0, 0.0, 16.0, 8.0 ] },
                "south": { "texture": "#0", "uv": [ 14.0, 0.0, 16.0, 8.0 ] },
                "west": { "texture": "#0", "uv": [ 14.0, 0.0, 16.0, 8.0 ] },
                "up": { "texture": "#0", "uv": [ 14.0, 0.0, 16.0, 2.0 ] },
                "down": { "texture": "#0", "uv": [ 14.0, 0.0, 16.0, 2.0 ] }
            }
        },
        {
            "name": "Support",
            "from": [ 10.0, 3.0, 4.0 ], 
            "to": [ 12.0, 15.0, 6.0 ], 
            "faces": {
                "north": { "texture": "#0", "uv": [ 14.0, 0.0, 16.0, 8.0 ] },
                "east": { "texture": "#0", "uv": [ 14.0, 0.0, 16.0, 8.0 ] },
                "south": { "texture": "#0", "uv": [ 14.0, 0.0, 16.0, 8.0 ] },
                "west": { "texture": "#0", "uv": [ 14.0, 0.0, 16.0, 8.0 ] },
                "up": { "texture": "#0", "uv": [ 14.0, 0.0, 16.0, 2.0 ] },
                "down": { "texture": "#0", "uv": [ 14.0, 0.0, 16.0, 2.0 ] }
            }
        },
        {
            "name": "Support",
            "from": [ 10.0, 3.0, 10.0 ], 
            "to": [ 12.0, 15.0, 12.0 ], 
            "faces": {
                "north": { "texture": "#0", "uv": [ 14.0, 0.0, 16.0, 8.0 ] },
                "east": { "texture": "#0", "uv": [ 14.0, 0.0, 16.0, 8.0 ] },
                "south": { "texture": "#0", "uv": [ 14.0, 0.0, 16.0, 8.0 ] },
                "west": { "texture": "#0", "uv": [ 14.0, 0.0, 16.0, 8.0 ] },
                "up": { "texture": "#0", "uv": [ 14.0, 0.0, 16.0, 2.0 ] },
                "down": { "texture": "#0", "uv": [ 14.0, 0.0, 16.0, 2.0 ] }
            }
        },
        {
            "name": "Support",
            "from": [ 4.0, 3.0, 10.0 ], 
            "to": [ 6.0, 15.0, 12.0 ], 
            "faces": {
                "north": { "texture": "#0", "uv": [ 14.0, 0.0, 16.0, 8.0 ] },
                "east": { "texture": "#0", "uv": [ 14.0, 0.0, 16.0, 8.0 ] },
                "south": { "texture": "#0", "uv": [ 14.0, 0.0, 16.0, 8.0 ] },
                "west": { "texture": "#0", "uv": [ 14.0, 0.0, 16.0, 8.0 ] },
                "up": { "texture": "#0", "uv": [ 14.0, 0.0, 16.0, 2.0 ] },
                "down": { "texture": "#0", "uv": [ 14.0, 0.0, 16.0, 2.0 ] }
            }
        }
    ]
}